.gitignore
LICENSE.txt
Makefile
README.md
requirements.txt
requirements_dev.txt
setup.py
pypiwik/__init__.py
pypiwik/decorators.py
pypiwik/tracker.py
python_piwik.egg-info/PKG-INFO
python_piwik.egg-info/SOURCES.txt
python_piwik.egg-info/dependency_links.txt
python_piwik.egg-info/not-zip-safe
python_piwik.egg-info/top_level.txt
tests/__main__.py
tests/builder.py
tests/decorators.py
tests/tracker.py