Metadata-Version: 1.1
Name: python-piwik
Version: 0.2
Summary: Python implementation of the Piwik HTTP API
Home-page: https://ercpe.de/projects/pypiwik
Author: Johann Schmitz
Author-email: johann@j-schmitz.net
License: GPL-3
Download-URL: https://code.not-your-server.de/pypiwik.git/tags/
Platform: UNKNOWN
